__init__.py
misspelling_lib/__init__.py
misspelling_lib/misspelling_checker.py
misspelling_lib/misspelling_detector.py
misspelling_lib/misspelling_factory.py
misspelling_lib/misspelling_file_detector.py
misspelling_lib/misspelling_interface.py
misspelling_lib/misspelling_json_detector.py
misspelling_lib/misspellings.py
misspelling_lib/json_sources/wikipedia.json
misspelling_lib/utils/__init__.py
misspelling_lib/utils/argument_parser.py
misspelling_lib/utils/files.py
misspelling_lib/utils/suggestions.py
misspelling_lib/utils/version.py
misspelling_lib/utils/words.py
misspellings_lib-2.0.9.dist-info/LICENSE
misspellings_lib-2.0.9.dist-info/METADATA
misspellings_lib-2.0.9.dist-info/WHEEL
misspellings_lib-2.0.9.dist-info/entry_points.txt
misspellings_lib-2.0.9.dist-info/top_level.txt
misspellings_lib-2.0.9.dist-info/RECORD
