Metadata-Version: 2.1
Name: misspellings-lib
Version: 2.0.9
Summary: A tool to detect misspellings with opinionated additions
Home-page: https://github.com/mazulo/misspelling
Download-URL: https://github.com/mazulo/misspelling/tarball/2.0.9
Author: Patrick Mazulo
Author-email: pmazulo@gmail.com
License: MIT License
Keywords: check,code,spelling,spellcheck
Platform: POSIX
Classifier: Development Status :: 5 - Production/Stable
Classifier: Environment :: Console
Classifier: License :: OSI Approved :: GNU General Public License v3 (GPLv3)
Classifier: Operating System :: OS Independent
Classifier: Programming Language :: Python :: 3
Classifier: Programming Language :: Python :: 3.7
Classifier: Programming Language :: Python :: 3.8
Classifier: Programming Language :: Python :: 3.9
Classifier: Programming Language :: Python :: 3.10
Classifier: Topic :: Utilities
License-File: LICENSE
Requires-Dist: typed-argument-parser (==1.7.2)
Requires-Dist: rich (==12.6.0)
